MANIFEST.in
README.md
setup.cfg
setup.py
101703196_topsis.egg-info/PKG-INFO
101703196_topsis.egg-info/SOURCES.txt
101703196_topsis.egg-info/dependency_links.txt
101703196_topsis.egg-info/top_level.txt
topsis/__init__.py
topsis/topsis.py