Metadata-Version: 2.1
Name: 101703196-topsis
Version: 1.0.0
Summary: topsis implementation
Home-page: https://github.com/guneesha12/101703196_topsis/tree/v_1.0.0
Author: Guneesha Sehgal
Author-email: guneeshasehgal@gmail.com
License: UNKNOWN
Download-URL: https://github.com/guneesha12/101703196_topsis/archive/v_1.0.0.tar.gz
Platform: UNKNOWN
Classifier: Programming Language :: Python :: 3
Classifier: License :: OSI Approved :: MIT License
Classifier: Operating System :: OS Independent
Requires-Python: >=3.6
